setup.py
zwdlib/__init__.py
zwdlib/agent.py
zwdlib/agent_lite.py
zwdlib/chinaz_words.py
zwdlib/configer.py
zwdlib/etao.py
zwdlib/longtail.py
zwdlib/rectangle.py
zwdlib/struct_views.py
zwdlib/test.py
zwdlib/tool_db.py
zwdlib/tool_django.py
zwdlib/tool_email.py
zwdlib/tool_env.py
zwdlib/tool_html.py
zwdlib/tool_keyword.py
zwdlib/tool_net.py
zwdlib/tool_svm.py
zwdlib.egg-info/PKG-INFO
zwdlib.egg-info/SOURCES.txt
zwdlib.egg-info/dependency_links.txt
zwdlib.egg-info/top_level.txt
zwdlib/pysvm/__init__.py
zwdlib/pysvm/tool_pysvm.py
zwdlib/pysvm/tool_svm.py