Metadata-Version: 1.0
Name: zwdlib
Version: 0.0.3
Summary: most common used tools
Home-page: UNKNOWN
Author: winston
Author-email: a18190@qq.com
License: MIT License
Keywords: common,tools
Platform: any
